nonebot_plugin_l4d2_server-1.1.6.dist-info/METADATA
nonebot_plugin_l4d2_server-1.1.6.dist-info/WHEEL
nonebot_plugin_l4d2_server-1.1.6.dist-info/entry_points.txt
nonebot_plugin_l4d2_server-1.1.6.dist-info/licenses/LICENSE
nonebot_plugin_l4d2_server/__init__.py
nonebot_plugin_l4d2_server/__main__.py
nonebot_plugin_l4d2_server/config.py
nonebot_plugin_l4d2_server/data/font/loli.ttf
nonebot_plugin_l4d2_server/l4_help/Help.json
nonebot_plugin_l4d2_server/l4_help/__init__.py
nonebot_plugin_l4d2_server/l4_help/draw.py
nonebot_plugin_l4d2_server/l4_help/icon/介绍.png
nonebot_plugin_l4d2_server/l4_help/icon/任务.png
nonebot_plugin_l4d2_server/l4_help/icon/信息.png
nonebot_plugin_l4d2_server/l4_help/icon/公告.png
nonebot_plugin_l4d2_server/l4_help/icon/刀剑.png
nonebot_plugin_l4d2_server/l4_help/icon/切换.png
nonebot_plugin_l4d2_server/l4_help/icon/删除.png
nonebot_plugin_l4d2_server/l4_help/icon/刷新.png
nonebot_plugin_l4d2_server/l4_help/icon/卡组.png
nonebot_plugin_l4d2_server/l4_help/icon/哪里.png
nonebot_plugin_l4d2_server/l4_help/icon/地图.png
nonebot_plugin_l4d2_server/l4_help/icon/导入.png
nonebot_plugin_l4d2_server/l4_help/icon/导出.png
nonebot_plugin_l4d2_server/l4_help/icon/影.png
nonebot_plugin_l4d2_server/l4_help/icon/拼图.png
nonebot_plugin_l4d2_server/l4_help/icon/探索.png
nonebot_plugin_l4d2_server/l4_help/icon/推送.png
nonebot_plugin_l4d2_server/l4_help/icon/收集.png
nonebot_plugin_l4d2_server/l4_help/icon/攻略.png
nonebot_plugin_l4d2_server/l4_help/icon/更新.png
nonebot_plugin_l4d2_server/l4_help/icon/材料.png
nonebot_plugin_l4d2_server/l4_help/icon/查询.png
nonebot_plugin_l4d2_server/l4_help/icon/校验.png
nonebot_plugin_l4d2_server/l4_help/icon/每月.png
nonebot_plugin_l4d2_server/l4_help/icon/深渊.png
nonebot_plugin_l4d2_server/l4_help/icon/添加.png
nonebot_plugin_l4d2_server/l4_help/icon/清除.png
nonebot_plugin_l4d2_server/l4_help/icon/状态.png
nonebot_plugin_l4d2_server/l4_help/icon/签到.png
nonebot_plugin_l4d2_server/l4_help/icon/绑定.png
nonebot_plugin_l4d2_server/l4_help/icon/表.png
nonebot_plugin_l4d2_server/l4_help/icon/表情.png
nonebot_plugin_l4d2_server/l4_help/icon/角色.png
nonebot_plugin_l4d2_server/l4_help/icon/记录.png
nonebot_plugin_l4d2_server/l4_help/icon/配置.png
nonebot_plugin_l4d2_server/l4_help/icon/重启.png
nonebot_plugin_l4d2_server-1.1.6.dist-info/RECORD
