Metadata-Version: 2.1
Name: nonebot-plugin-l4d2-server
Version: 1.1.6
Summary: L4D2 server related operations plugin for NoneBot2
Keywords: steam,game,l4d2,nonebot2,plugin
Author-Email: Agnes_Digital <Z735803792@163.com>
License: GPLv3
Classifier: License :: OSI Approved :: GNU General Public License v3 (GPLv3)
Classifier: Programming Language :: Python
Classifier: Programming Language :: Python :: 3
Classifier: Programming Language :: Python :: 3.9
Classifier: Programming Language :: Python :: 3.10
Classifier: Programming Language :: Python :: 3.11
Classifier: Programming Language :: Python :: 3.12
Classifier: Operating System :: OS Independent
Project-URL: homepage, https://github.com/Agnes4m/nonebot_plugin_l4d2_server
Requires-Python: <4.0,>=3.9
Requires-Dist: nonebot2>=2.1.0
Requires-Dist: nonebot2[fastapi]>=2.3.3
Requires-Dist: nonebot-plugin-htmlrender>=0.3.0
Requires-Dist: nonebot-adapter-onebot>=2.4.4
Requires-Dist: nonebot-plugin-alconna>=0.50.0
Requires-Dist: nonebot_plugin_datastore>=1.3.0
Requires-Dist: nonebot-plugin-tortoise-orm>=0.1.4
Requires-Dist: aiohttp>=3.8.4
Requires-Dist: jinja2>=3.0.0
Requires-Dist: srctools>=2.6.0
Requires-Dist: httpx>=0.22.0
Requires-Dist: python-a2s>=1.4.1
Requires-Dist: ujson>=5.10.0
Requires-Dist: rcon>=2.1.0
Requires-Dist: pillow>10.0.0
Requires-Dist: rarfile>=4.2
Requires-Dist: pyunpack>=0.3
Requires-Dist: aiofiles>=24.1.0
Requires-Dist: bs4==0.0.2
